rag_agent/__init__.py
rag_agent/__main__.py
rag_agent/app.py
rag_agent/api/__init__.py
rag_agent/api/rag.py
rag_agent/core/__init__.py
rag_agent/core/config.py
rag_agent/core/enums.py
rag_agent/core/logging_config.py
rag_agent/core/model_client.py
rag_agent/core/prompt_templates/__init__.py
rag_agent/core/prompt_templates/default.py
rag_agent/core/prompt_templates/direct_chat.py
rag_agent/core/prompt_templates/hyde_template.py
rag_agent/core/prompt_templates/multiple_references_template.py
rag_agent/core/prompt_templates/ner_keyword_extractor_template.py
rag_agent/demos/demo_user_query_document.py
rag_agent/schemas/rag.py
rag_agent/security/auth.py
rag_agent/services/__init__.py
rag_agent/services/ner_extractor.py
rag_agent/services/rag.py
rag_agent/services/retriever/base_retriever.py
rag_agent/services/retriever/bm25.py
rag_agent/services/retriever/hybrid.py
rag_agent/services/retriever/two_stage.py
rag_agent/services/retriever/vector.py
csha_ai_agent-0.3.0.dist-info/METADATA
csha_ai_agent-0.3.0.dist-info/WHEEL
csha_ai_agent-0.3.0.dist-info/entry_points.txt
csha_ai_agent-0.3.0.dist-info/top_level.txt
csha_ai_agent-0.3.0.dist-info/RECORD
