Metadata-Version: 2.4
Name: csha-ai-agent
Version: 0.3.0
Summary: FastAPI service for the CSHA AI Agent (RAG-powered question answering over CSHA documents and website data)
Author-email: Leonard Jin <leonard.jin.0707@gmail.com>
License: Proprietary
Requires-Python: >=3.9.6
Requires-Dist: nltk>=3.9
Requires-Dist: rank-bm25>=0.2.2
Requires-Dist: pinecone>=7.2.0
Requires-Dist: numpy>=2.3
Requires-Dist: langchain>=0.3.26
Requires-Dist: langchain-openai>=0.3.26
Requires-Dist: langchain-pinecone>=0.2.8
Requires-Dist: pydantic>=2.11
Requires-Dist: pydantic-settings>=2.10
Requires-Dist: fastapi>=0.116.1
Requires-Dist: uvicorn[standard]>=0.35.0
Requires-Dist: psycopg[binary]>=3.2.0
Requires-Dist: psycopg-pool>=3.2.0
Requires-Dist: httpx>=0.27.0
Requires-Dist: python-multipart>=0.0.9
